{
  "slug": "shorts-mini-uv-umbrella-quick-check-2026",
  "title": "숏츠 쇼핑픽 — 초경량 UV 우산, 60초 안에 확인할 3가지",
  "description": "출근·여행 가방에 넣을 초경량 UV 우산을 빠르게 고를 때는 무게, 차광·UV 표기, 접었을 때 길이와 내구성을 먼저 확인하면 됩니다.",
  "date": "2026-07-07T18:43:00+09:00",
  "category": "숏츠 쇼핑픽",
  "tags": ["숏츠 쇼핑픽", "구매가이드", "초경량 우산", "UV 차단", "양우산", "여름 생활용품"],
  "is_affiliate": false,
  "body_html": "<p>초경량 UV 우산은 숫자가 많아 보여도 빠르게 보면 됩니다. <strong>무게, 차광·UV 표기, 접었을 때 길이와 내구성</strong> 이 3가지만 먼저 확인하세요. 특정 제품 순위가 아니라 빠른 구매 판단 기준입니다.</p>\n<h2>60초 체크</h2>\n<ol>\n<li><strong>무게는 매일 들 수 있는가?</strong> — 출근 가방 상시 휴대라면 가벼운 쪽이 좋습니다. 다만 너무 가벼운 제품은 살대 내구성도 같이 확인하세요.</li>\n<li><strong>UV·차광 표기가 명확한가?</strong> — 양산 겸용이면 UV 차단율, 암막 코팅, 안쪽 코팅 마감이 중요합니다. 표기가 모호하면 기대치를 낮추는 편이 안전합니다.</li>\n<li><strong>접은 길이와 펼친 크기</strong> — 가방에는 들어가도 펼쳤을 때 어깨가 젖을 수 있습니다. 1인용인지, 비바람에 약한 구조인지 확인하세요.</li>\n</ol>\n<h2>한 줄 결론</h2>\n<p><strong>매일 휴대할 무게 + 명확한 UV 표기 + 접은 길이/살대 내구성</strong>을 통과하면 초경량 UV 우산은 대체로 만족도가 높습니다. 여행용은 작게, 장마용은 내구성을 더 우선하세요.</p>"
}
